Workbook

Sheet Recommendation
A1: Basil — Backend Platform Comparison
A2: HIPAA-gated scored comparison · April 2026 · v0.1
A4: Context
A5: Basil will plan for HIPAA from day one. That removes several otherwise strong platforms from the shortlist, because they either do not offer a BAA at all, or only on tiers that are not right-sized for a pre-product-market-fit startup. This model scores the remaining realistic candidates against weighted criteria.
A9: TL;DR Recommendation
A10: Start on Supabase Team plan (HIPAA add-on, ~$599/mo) for MVP + closed beta. It gives you Postgres, auth, realtime, storage, and a BAA in a single vendor so one-person ops stays sane. Design the backend with a thin, platform-agnostic API layer (your own REST/GraphQL service in front of Postgres) so migration to AWS with Aurora + Cognito + AppSync remains possible if the company crosses into enterprise / payor deals where AWS is table stakes.
A15: Shortlist at a glance
A16: Platform | B16: BAA posture | C16: Monthly floor (HIPAA) | D16: Best for | E16: Verdict | F16: Score
A17: Supabase (Team + HIPAA) | B17: BAA on Team plan | C17: $599 | D17: MVP → v1 for a solo dev | E17: Recommended starter | F17: =Scorecard!L6 -> 4.35
A18: AWS (Aurora+Cognito+AppSync) | B18: BAA default; most mature | C18: ~$200–400 at low scale; grows fast | D18: Scale, enterprise sales | E18: Migrate target | F18: =Scorecard!L7 -> 3.81
A19: GCP (Firestore+Identity+BAA) | B19: BAA on eligible services only | C19: ~$150–300 | D19: If team already in GCP | E19: Viable; Firestore scaling gotchas | F19: =Scorecard!L8 -> 3.6
A20: Firebase (selective) | B20: BAA on some services, not all | C20: ~$100–300 | D20: Tempting but risky scope | E20: Avoid unless surgically scoped | F20: =Scorecard!L9 -> 3.53
A21: Aptible | B21: HIPAA-native PaaS | C21: ~$499 | D21: Wanting compliance out-of-the-box | E21: Viable but pricey per-unit | F21: =Scorecard!L10 -> 3.53
A22: Fly.io (Enterprise) | B22: BAA on Enterprise | C22: ~Custom | D22: Edge-distributed container apps | E22: Solid infra, immature managed DB | F22: =Scorecard!L11 -> 3.36
A23: Azure (HIPAA-eligible) | B23: BAA default | C23: ~$200–400 | D23: Microsoft-shop enterprises | E23: Fine, but no reason to pick | F23: =Scorecard!L12 -> 3.66
A24: Convex | B24: No public HIPAA BAA | C24: n/a | D24: (non-HIPAA projects) | E24: Disqualified for current scope | F24: =Scorecard!L14 -> 3.08
A27: How we decided
A28: 1. HIPAA BAA must be available at a price point that works for a pre-revenue startup. Hyperscalers all qualify; most startup-friendly PaaS do not.
A29: 2. One-person ops: strong preference for managed Postgres + managed auth + managed realtime from a single vendor.
A30: 3. KMP-friendly: any backend we pick talks HTTP/REST/GraphQL from Kotlin Multiplatform without heroics. We explicitly do not want a proprietary KMP-hostile SDK on the critical path.
A31: 4. Portability: we accept slight migration cost later in exchange for speed now. Escape hatch preserved via an API layer we own.
A32: 5. Data residency: US-only region for launch; EU region added when we expand.

Sheet Scorecard
A1: Weighted Scorecard (1–5; higher is better)
A2: Blue cells are editable inputs. Weights in row 4 sum to 100%. Weighted score in row 16+ is =SUMPRODUCT(scores, weights).
L3: Σ weights
A4: Weight → | B4: 0.2 | C4: 0.1 | D4: 0.1 | E4: 0.1 | F4: 0.08 | G4: 0.1 | H4: 0.12 | I4: 0.08 | J4: 0.07 | K4: 0.05 | L4: =SUM(B4:K4) -> 1
A5: Criterion | B5: HIPAA / BAA posture | C5: Managed Postgres quality | D5: Auth maturity | E5: Realtime / offline sync | F5: KMP client fit | G5: Dev ergonomics / DX | H5: Cost at 100k MAU | I5: Vendor lock-in risk | J5: Ops burden (solo-dev) | K5: Ecosystem / community | L5: Weighted Score | M5: Rank
A6: Supabase (Team+HIPAA) | B6: 5 | C6: 4 | D6: 4 | E6: 5 | F6: 4 | G6: 5 | H6: 3 | I6: 4 | J6: 5 | K6: 4 | L6: =SUMPRODUCT(B6:K6,B$4:K$4) -> 4.35 | M6: =RANK(L6,$L$6:$L$14) -> 1
A7: AWS (Aurora+Cognito+AppSync) | B7: 5 | C7: 5 | D7: 4 | E7: 4 | F7: 3 | G7: 2 | H7: 3 | I7: 4 | J7: 2 | K7: 5 | L7: =SUMPRODUCT(B7:K7,B$4:K$4) -> 3.81 | M7: =RANK(L7,$L$6:$L$14) -> 2
A8: GCP (Firestore+Identity) | B8: 4 | C8: 3 | D8: 4 | E8: 5 | F8: 3 | G8: 3 | H8: 3 | I8: 3 | J8: 3 | K8: 5 | L8: =SUMPRODUCT(B8:K8,B$4:K$4) -> 3.6 | M8: =RANK(L8,$L$6:$L$14) -> 4
A9: Firebase (selective) | B9: 3 | C9: 2 | D9: 5 | E9: 5 | F9: 2 | G9: 4 | H9: 4 | I9: 2 | J9: 4 | K9: 5 | L9: =SUMPRODUCT(B9:K9,B$4:K$4) -> 3.53 | M9: =RANK(L9,$L$6:$L$14) -> 5
A10: Aptible PaaS | B10: 5 | C10: 4 | D10: 2 | E10: 2 | F10: 4 | G10: 4 | H10: 2 | I10: 4 | J10: 5 | K10: 2 | L10: =SUMPRODUCT(B10:K10,B$4:K$4) -> 3.53 | M10: =RANK(L10,$L$6:$L$14) -> 5
A11: Fly.io (Enterprise) | B11: 4 | C11: 3 | D11: 2 | E11: 3 | F11: 4 | G11: 4 | H11: 3 | I11: 4 | J11: 3 | K11: 3 | L11: =SUMPRODUCT(B11:K11,B$4:K$4) -> 3.36 | M11: =RANK(L11,$L$6:$L$14) -> 8
A12: Azure (HIPAA-eligible) | B12: 5 | C12: 4 | D12: 4 | E12: 3 | F12: 3 | G12: 3 | H12: 3 | I12: 4 | J12: 2 | K12: 4 | L12: =SUMPRODUCT(B12:K12,B$4:K$4) -> 3.66 | M12: =RANK(L12,$L$6:$L$14) -> 3
A13: Render (Team+HIPAA) | B13: 4 | C13: 4 | D13: 3 | E13: 2 | F13: 4 | G13: 4 | H13: 3 | I13: 4 | J13: 4 | K13: 3 | L13: =SUMPRODUCT(B13:K13,B$4:K$4) -> 3.53 | M13: =RANK(L13,$L$6:$L$14) -> 5
A14: Convex (non-HIPAA) | B14: 0 | C14: 3 | D14: 4 | E14: 5 | F14: 3 | G14: 5 | H14: 4 | I14: 2 | J14: 5 | K14: 3 | L14: =SUMPRODUCT(B14:K14,B$4:K$4) -> 3.08 | M14: =RANK(L14,$L$6:$L$14) -> 9
A17: Scoring rubric
A18: 5 = Best in category; clearly the right choice on this dimension
A19: 4 = Strong
A20: 3 = Adequate
A21: 2 = Weak but workable
A22: 1 = Poor
A23: 0 = Disqualifying (e.g. no HIPAA BAA when HIPAA is required)

Sheet HIPAA Details
A1: HIPAA / BAA posture by platform
A2: What you actually need to know before signing anything.
A4: Platform | B4: BAA available? | C4: Eligible services / caveats | D4: What to watch out for
A5: AWS | B5: Yes, default on Business Support+ | C5: Most services eligible; check the AWS BAA service list. Aurora, Cognito, AppSync, S3, Lambda, CloudFront, KMS all covered. | D5: You sign one BAA with AWS; still must configure encryption, logging, KMS. Support tier requirement raises floor cost.
A6: GCP | B6: Yes | C6: Eligible services listed in Google's BAA; Firestore, Cloud Run, Cloud SQL, Identity Platform, Pub/Sub covered. | D6: Firebase services need individual review — not all Firebase is HIPAA-covered. Analytics and Crashlytics are NOT covered.
A7: Azure | B7: Yes | C7: Most Azure services eligible under Microsoft's BAA. | D7: Sensible if your team is already in Microsoft's world; not obviously better than AWS for a greenfield app.
A8: Firebase (selectively) | B8: Partial — service by service | C8: HIPAA-eligible: Cloud Firestore, Cloud Functions, Cloud Storage, Hosting, App Check. NOT eligible: Analytics, Crashlytics, Realtime Database, Cloud Messaging (FCM) data. | D8: Easy to accidentally put PHI into a non-eligible Firebase service. Operationally risky for HIPAA.
A9: Supabase | B9: Yes, on Team plan + HIPAA add-on | C9: Postgres, Auth, Realtime, Storage, Edge Functions all covered under BAA when HIPAA add-on is enabled. $599/mo floor including Team plan + HIPAA add-on. | D9: Relatively new HIPAA offering (GA 2024). Community-maintained open source so you can self-host if ever needed.
A10: Aptible | B10: Yes, native | C10: PaaS built for HIPAA-regulated software; ships with encryption, logging, audit trail, intrusion detection. | D10: Higher per-unit cost; you're paying for compliance-as-a-service. Excellent if you want to trade money for ops burden.
A11: Fly.io | B11: Yes, on Enterprise plan | C11: Containers + managed Postgres (still labeled beta at last check). BAA available with Enterprise. | D11: Managed Postgres maturity; volume-based pricing; less friendly for 1-person ops than Supabase.
A12: Render | B12: Yes, on Team/Enterprise | C12: Managed Postgres + services + background workers; BAA on Team HIPAA tier. | D12: Smaller ecosystem than Fly/Supabase; good dev UX; fine option.
A13: Convex | B13: No public BAA at time of writing | C13: Reactive backend with excellent DX, but not HIPAA-eligible per public docs. | D13: Disqualified from this selection if PHI ever lives server-side. Confirm directly with Convex before using.
A14: Vercel / Netlify | B14: Enterprise BAA possible | C14: For static/edge functions only; not for PHI storage. | D14: Use as edge/CDN in front of a HIPAA-eligible origin; never as a primary data store.
A15: Auth providers (Auth0, Clerk, Stytch) | B15: Auth0: Yes. Clerk: HIPAA tier. Stytch: HIPAA tier. | C15: Review whether you need a separate auth vendor if the backend already provides it (Supabase Auth / Cognito). | D15: Each extra BAA is an extra vendor to manage. Prefer bundling unless there's a strong reason.
... A17: Analytics / Crashlytics | B17: PostHog Cloud: HIPAA tier. Aptabase: self-hostable. Sentry: BAA on Business. | C17: Do not send PHI here. Use user IDs that are not PHI. | D17: A common source of HIPAA compliance drift — audit what you send before GA.

Sheet Cost Model
A1: Monthly cost at scale (order-of-magnitude)
A2: Blue cells are assumptions you can change. Black cells are formulas. Caveat: public pricing; real cost varies.
A4: Assumptions (editable)
A5: Assumption | B5: Value | C5: Unit | D5: Notes
A6: Per-user monthly DB storage (MB) | B6: 5 | C6: MB | D6: Estimate: ~150 log entries/mo + CGM data if synced
A7: Per-user monthly egress (MB) | B7: 10 | C7: MB | D7: App pulls + report export
A8: Per-user monthly request count | B8: 1500 | C8: requests | D8: Assume 50 req/day per MAU average
A9: Monthly active users (MAU) | B9: 10000 | C9: users | D9: Change this to re-run all scenarios
A10: Paid user % | B10: 0 | C10: % | D10: No monetization until v2; placeholder for later
A13: Estimated monthly floor by platform (US region)
A14: Platform | B14: Fixed monthly floor ($) | C14: Per-MAU variable ($) | D14: Est. monthly at current MAU ($) | E14: Notes
A15: Supabase (Team + HIPAA add-on) | B15: 599 | C15: 0.02 | D15: =B15+C15*$B9 -> 799 | E15: Flat Team tier $599 (incl. HIPAA add-on); DB/egress included up to generous caps; scales in tier bumps.
A16: AWS (Aurora Serverless + Cognito + AppSync) | B16: 150 | C16: 0.04 | D16: =B16+C16*$B9 -> 550 | E16: Aurora Serverless min; Cognito free up to 50k MAU; AppSync per-request; S3 per-GB.
A17: GCP (Firestore + Identity Platform) | B17: 50 | C17: 0.05 | D17: =B17+C17*$B9 -> 550 | E17: Firestore per-read/write pricing can spike; audit query patterns.
A18: Firebase (Firestore + Cloud Functions) | B18: 25 | C18: 0.05 | D18: =B18+C18*$B9 -> 525 | E18: Similar to GCP; watch Cloud Function invocations.
A19: Aptible PaaS | B19: 499 | C19: 0.03 | D19: =B19+C19*$B9 -> 799 | E19: $499 Starter; scales per-container; simpler to reason about.
A20: Fly.io (Enterprise) | B20: 200 | C20: 0.025 | D20: =B20+C20*$B9 -> 450 | E20: Volume-based; cheaper at edge but managed Postgres less mature.
A21: Azure (Cosmos DB / SQL + B2C) | B21: 200 | C21: 0.04 | D21: =B21+C21*$B9 -> 600 | E21: Comparable to AWS; pick if already Microsoft-shop.
A22: Render (Team HIPAA) | B22: 250 | C22: 0.02 | D22: =B22+C22*$B9 -> 450 | E22: Smaller ecosystem but clean UX; Postgres good.
A26: Scenario — cost at 10k / 100k / 1M MAU
A27: Platform | B27: @ 10k MAU ($/mo) | C27: @ 100k MAU ($/mo) | D27: @ 1M MAU ($/mo)
A28: Supabase (Team + HIPAA add-on) | B28: =B15+C15*10000 -> 799 | C28: =B15+C15*100000 -> 2599 | D28: =B15+C15*1000000 -> 20599
A29: AWS (Aurora Serverless + Cognito + AppSync) | B29: =B16+C16*10000 -> 550 | C29: =B16+C16*100000 -> 4150 | D29: =B16+C16*1000000 -> 40150
A30: GCP (Firestore + Identity Platform) | B30: =B17+C17*10000 -> 550 | C30: =B17+C17*100000 -> 5050 | D30: =B17+C17*1000000 -> 50050
A31: Firebase (Firestore + Cloud Functions) | B31: =B18+C18*10000 -> 525 | C31: =B18+C18*100000 -> 5025 | D31: =B18+C18*1000000 -> 50025
A32: Aptible PaaS | B32: =B19+C19*10000 -> 799 | C32: =B19+C19*100000 -> 3499 | D32: =B19+C19*1000000 -> 30499
A33: Fly.io (Enterprise) | B33: =B20+C20*10000 -> 450 | C33: =B20+C20*100000 -> 2700 | D33: =B20+C20*1000000 -> 25200
A34: Azure (Cosmos DB / SQL + B2C) | B34: =B21+C21*10000 -> 600 | C34: =B21+C21*100000 -> 4200 | D34: =B21+C21*1000000 -> 40200
A35: Render (Team HIPAA) | B35: =B22+C22*10000 -> 450 | C35: =B22+C22*100000 -> 2250 | D35: =B22+C22*1000000 -> 20250

Sheet Sources & Caveats
A1: Sources & caveats
A2: Public pricing and BAA posture change frequently. Confirm before committing.
A4: Pricing | B4: All dollar figures are order-of-magnitude from public pricing pages, not negotiated rates. Actual cost at scale varies 2–5x based on query patterns, data transfer, and support tier.
A5: HIPAA BAA availability | B5: Verified against each vendor's public docs as of early 2026. Vendor offerings change — confirm at contract time.
A6: Firebase caveat | B6: Firebase is the most compliance-risky option because individual services have different BAA statuses. Treat as avoid-unless-surgically-scoped.
A7: Convex | B7: Convex is excellent for non-PHI workloads. Basil's HIPAA-from-day-one posture rules it out unless it ships a BAA offering.
A8: Scoring subjectivity | B8: Scores are one person's informed opinion, not a formal benchmark. Edit weights and scores to reflect your own reading of the tradeoffs.
A9: Not included | B9: Heroku (HIPAA offering discontinued to new customers), DigitalOcean (no HIPAA BAA), Railway (no HIPAA), PlanetScale (no HIPAA), Neon (no public HIPAA BAA at time of writing).
A10: Recommended next step | B10: Once the decision is made, spike a 2-week proof-of-concept: auth, a protected endpoint, an encrypted-at-rest log write, and a full round-trip from the Kotlin app. That surfaces ergonomics problems faster than any comparison.
